[
  {
    "name": "户山香澄",
    "mmdd": "07-14",
    "kind": "character",
    "color": "#FF5522",
    "link": "/orgs/poppinparty",
    "org": "ppp",
    "seiyuu": "爱美"
  },
  {
    "name": "爱美",
    "mmdd": "12-25",
    "kind": "seiyuu",
    "color": "#FF997A",
    "link": "",
    "org": "ppp",
    "seiyuu": ""
  },
  {
    "name": "花园多惠",
    "mmdd": "12-04",
    "kind": "character",
    "color": "#0077DD",
    "link": "/orgs/poppinparty",
    "org": "ppp",
    "seiyuu": "大冢纱英"
  },
  {
    "name": "大冢纱英",
    "mmdd": "10-10",
    "kind": "seiyuu",
    "color": "#66ADEA",
    "link": "",
    "org": "ppp",
    "seiyuu": ""
  },
  {
    "name": "牛込里美",
    "mmdd": "03-23",
    "kind": "character",
    "color": "#FF55BB",
    "link": "/orgs/poppinparty",
    "org": "ppp",
    "seiyuu": "西本里美"
  },
  {
    "name": "西本里美",
    "mmdd": "10-25",
    "kind": "seiyuu",
    "color": "#FF99D6",
    "link": "",
    "org": "ppp",
    "seiyuu": ""
  },
  {
    "name": "山吹沙绫",
    "mmdd": "05-19",
    "kind": "character",
    "color": "#FFCC11",
    "link": "/orgs/poppinparty",
    "org": "ppp",
    "seiyuu": "大桥彩香"
  },
  {
    "name": "大桥彩香",
    "mmdd": "09-13",
    "kind": "seiyuu",
    "color": "#FFE070",
    "link": "",
    "org": "ppp",
    "seiyuu": ""
  },
  {
    "name": "市谷有咲",
    "mmdd": "10-27",
    "kind": "character",
    "color": "#AA66DD",
    "link": "/orgs/poppinparty",
    "org": "ppp",
    "seiyuu": "伊藤彩沙"
  },
  {
    "name": "伊藤彩沙",
    "mmdd": "08-17",
    "kind": "seiyuu",
    "color": "#CCA3EA",
    "link": "",
    "org": "ppp",
    "seiyuu": ""
  },
  {
    "name": "美竹兰",
    "mmdd": "04-10",
    "kind": "character",
    "color": "#EE0022",
    "link": "/orgs/afterglow",
    "org": "a",
    "seiyuu": "佐仓绫音"
  },
  {
    "name": "佐仓绫音",
    "mmdd": "01-29",
    "kind": "seiyuu",
    "color": "#F4667A",
    "link": "",
    "org": "a",
    "seiyuu": ""
  },
  {
    "name": "青叶摩卡",
    "mmdd": "09-03",
    "kind": "character",
    "color": "#00CCAA",
    "link": "/orgs/afterglow",
    "org": "a",
    "seiyuu": "三泽纱千香"
  },
  {
    "name": "三泽纱千香",
    "mmdd": "01-13",
    "kind": "seiyuu",
    "color": "#66E0CC",
    "link": "",
    "org": "a",
    "seiyuu": ""
  },
  {
    "name": "上原绯玛丽",
    "mmdd": "10-23",
    "kind": "character",
    "color": "#FF9999",
    "link": "/orgs/afterglow",
    "org": "a",
    "seiyuu": "加藤英美里"
  },
  {
    "name": "加藤英美里",
    "mmdd": "11-26",
    "kind": "seiyuu",
    "color": "#FFC1C1",
    "link": "",
    "org": "a",
    "seiyuu": ""
  },
  {
    "name": "宇田川巴",
    "mmdd": "04-15",
    "kind": "character",
    "color": "#BB0033",
    "link": "/orgs/afterglow",
    "org": "a",
    "seiyuu": "日笠阳子"
  },
  {
    "name": "日笠阳子",
    "mmdd": "07-16",
    "kind": "seiyuu",
    "color": "#D66684",
    "link": "",
    "org": "a",
    "seiyuu": ""
  },
  {
    "name": "羽泽鸫",
    "mmdd": "01-07",
    "kind": "character",
    "color": "#FFEE88",
    "link": "/orgs/afterglow",
    "org": "a",
    "seiyuu": "金元寿子"
  },
  {
    "name": "金元寿子",
    "mmdd": "12-16",
    "kind": "seiyuu",
    "color": "#FFF4B7",
    "link": "",
    "org": "a",
    "seiyuu": ""
  },
  {
    "name": "丸山彩",
    "mmdd": "12-27",
    "kind": "character",
    "color": "#FF88BB",
    "link": "/orgs/pastel-palettes",
    "org": "pp",
    "seiyuu": "前岛亚美"
  },
  {
    "name": "前岛亚美",
    "mmdd": "11-22",
    "kind": "seiyuu",
    "color": "#FFB7D6",
    "link": "",
    "org": "pp",
    "seiyuu": ""
  },
  {
    "name": "冰川日菜",
    "mmdd": "03-20",
    "kind": "character",
    "color": "#55DDEE",
    "link": "/orgs/pastel-palettes",
    "org": "pp",
    "seiyuu": "小泽亚李"
  },
  {
    "name": "小泽亚李",
    "mmdd": "08-10",
    "kind": "seiyuu",
    "color": "#99EAF4",
    "link": "",
    "org": "pp",
    "seiyuu": ""
  },
  {
    "name": "白鹭千圣",
    "mmdd": "04-06",
    "kind": "character",
    "color": "#FFEEAA",
    "link": "/orgs/pastel-palettes",
    "org": "pp",
    "seiyuu": "上坂堇"
  },
  {
    "name": "上坂堇",
    "mmdd": "12-19",
    "kind": "seiyuu",
    "color": "#FFF4CC",
    "link": "",
    "org": "pp",
    "seiyuu": ""
  },
  {
    "name": "大和麻弥",
    "mmdd": "11-03",
    "kind": "character",
    "color": "#99DD88",
    "link": "/orgs/pastel-palettes",
    "org": "pp",
    "seiyuu": "中上育实"
  },
  {
    "name": "中上育实",
    "mmdd": "06-18",
    "kind": "seiyuu",
    "color": "#C1EAB7",
    "link": "",
    "org": "pp",
    "seiyuu": ""
  },
  {
    "name": "若宫伊芙",
    "mmdd": "06-27",
    "kind": "character",
    "color": "#DDBBFF",
    "link": "/orgs/pastel-palettes",
    "org": "pp",
    "seiyuu": "秦佐和子"
  },
  {
    "name": "秦佐和子",
    "mmdd": "09-14",
    "kind": "seiyuu",
    "color": "#EAD6FF",
    "link": "",
    "org": "pp",
    "seiyuu": ""
  },
  {
    "name": "凑友希那",
    "mmdd": "10-26",
    "kind": "character",
    "color": "#881188",
    "link": "/orgs/roselia",
    "org": "r",
    "seiyuu": "相羽爱奈"
  },
  {
    "name": "相羽爱奈",
    "mmdd": "10-17",
    "kind": "seiyuu",
    "color": "#B770B7",
    "link": "",
    "org": "r",
    "seiyuu": ""
  },
  {
    "name": "冰川纱夜",
    "mmdd": "03-20",
    "kind": "character",
    "color": "#00AABB",
    "link": "/orgs/roselia",
    "org": "r",
    "seiyuu": "工藤晴香"
  },
  {
    "name": "工藤晴香",
    "mmdd": "03-16",
    "kind": "seiyuu",
    "color": "#66CCD6",
    "link": "",
    "org": "r",
    "seiyuu": ""
  },
  {
    "name": "今井莉莎",
    "mmdd": "08-25",
    "kind": "character",
    "color": "#DD2200",
    "link": "/orgs/roselia",
    "org": "r",
    "seiyuu": "远藤祐里香, 中岛由贵"
  },
  {
    "name": "远藤祐里香",
    "mmdd": "06-24",
    "kind": "seiyuu",
    "color": "#EA7A66",
    "link": "",
    "org": "r",
    "seiyuu": ""
  },
  {
    "name": "中岛由贵",
    "mmdd": "09-12",
    "kind": "seiyuu",
    "color": "#EA7A66",
    "link": "",
    "org": "r",
    "seiyuu": ""
  },
  {
    "name": "宇田川亚子",
    "mmdd": "07-03",
    "kind": "character",
    "color": "#DD0088",
    "link": "/orgs/roselia",
    "org": "r",
    "seiyuu": "樱川惠"
  },
  {
    "name": "樱川惠",
    "mmdd": "10-24",
    "kind": "seiyuu",
    "color": "#EA66B7",
    "link": "",
    "org": "r",
    "seiyuu": ""
  },
  {
    "name": "白金燐子",
    "mmdd": "10-17",
    "kind": "character",
    "color": "#BBBBBB",
    "link": "/orgs/roselia",
    "org": "r",
    "seiyuu": "明坂聪美, 志崎桦音"
  },
  {
    "name": "明坂聪美",
    "mmdd": "01-02",
    "kind": "seiyuu",
    "color": "#D6D6D6",
    "link": "",
    "org": "r",
    "seiyuu": ""
  },
  {
    "name": "志崎桦音",
    "mmdd": "02-08",
    "kind": "seiyuu",
    "color": "#D6D6D6",
    "link": "",
    "org": "r",
    "seiyuu": ""
  },
  {
    "name": "弦卷心",
    "mmdd": "08-08",
    "kind": "character",
    "color": "#FFEE22",
    "link": "/orgs/hello-happy-world",
    "org": "hhp",
    "seiyuu": "伊藤美来"
  },
  {
    "name": "伊藤美来",
    "mmdd": "10-12",
    "kind": "seiyuu",
    "color": "#FFF47A",
    "link": "",
    "org": "hhp",
    "seiyuu": ""
  },
  {
    "name": "濑田薰",
    "mmdd": "02-28",
    "kind": "character",
    "color": "#AA33CC",
    "link": "/orgs/hello-happy-world",
    "org": "hhp",
    "seiyuu": "田所梓"
  },
  {
    "name": "田所梓",
    "mmdd": "11-10",
    "kind": "seiyuu",
    "color": "#CC84E0",
    "link": "",
    "org": "hhp",
    "seiyuu": ""
  },
  {
    "name": "北泽育美",
    "mmdd": "07-30",
    "kind": "character",
    "color": "#FF9922",
    "link": "/orgs/hello-happy-world",
    "org": "hhp",
    "seiyuu": "吉田有里"
  },
  {
    "name": "吉田有里",
    "mmdd": "08-18",
    "kind": "seiyuu",
    "color": "#FFC17A",
    "link": "",
    "org": "hhp",
    "seiyuu": ""
  },
  {
    "name": "松原花音",
    "mmdd": "05-11",
    "kind": "character",
    "color": "#44DDFF",
    "link": "/orgs/hello-happy-world",
    "org": "hhp",
    "seiyuu": "丰田萌绘"
  },
  {
    "name": "丰田萌绘",
    "mmdd": "03-15",
    "kind": "seiyuu",
    "color": "#8EEAFF",
    "link": "",
    "org": "hhp",
    "seiyuu": ""
  },
  {
    "name": "奥泽美咲",
    "mmdd": "10-01",
    "kind": "character",
    "color": "#006699",
    "link": "/orgs/hello-happy-world",
    "org": "hhp",
    "seiyuu": "黑泽朋世"
  },
  {
    "name": "黑泽朋世",
    "mmdd": "04-10",
    "kind": "seiyuu",
    "color": "#66A3C1",
    "link": "",
    "org": "hhp",
    "seiyuu": ""
  },
  {
    "name": "米歇尔",
    "mmdd": "10-01",
    "kind": "character",
    "color": "#DD33CC",
    "link": "/orgs/hello-happy-world",
    "org": "hhp",
    "seiyuu": "黑泽朋世"
  },
  {
    "name": "黑泽朋世",
    "mmdd": "04-10",
    "kind": "seiyuu",
    "color": "#EA84E0",
    "link": "",
    "org": "hhp",
    "seiyuu": ""
  },
  {
    "name": "仓田真白",
    "mmdd": "02-19",
    "kind": "character",
    "color": "#6677CC",
    "link": "/orgs/morfonica",
    "org": "m",
    "seiyuu": "进藤天音"
  },
  {
    "name": "进藤天音",
    "mmdd": "04-20",
    "kind": "seiyuu",
    "color": "#A3ADE0",
    "link": "",
    "org": "m",
    "seiyuu": ""
  },
  {
    "name": "桐谷透子",
    "mmdd": "12-16",
    "kind": "character",
    "color": "#EE6666",
    "link": "/orgs/morfonica",
    "org": "m",
    "seiyuu": "直田姬奈"
  },
  {
    "name": "直田姬奈",
    "mmdd": "04-17",
    "kind": "seiyuu",
    "color": "#F4A3A3",
    "link": "",
    "org": "m",
    "seiyuu": ""
  },
  {
    "name": "广町七深",
    "mmdd": "06-16",
    "kind": "character",
    "color": "#EE7744",
    "link": "/orgs/morfonica",
    "org": "m",
    "seiyuu": "西尾夕香"
  },
  {
    "name": "西尾夕香",
    "mmdd": "03-31",
    "kind": "seiyuu",
    "color": "#F4AD8E",
    "link": "",
    "org": "m",
    "seiyuu": ""
  },
  {
    "name": "二叶筑紫",
    "mmdd": "09-15",
    "kind": "character",
    "color": "#EE7788",
    "link": "/orgs/morfonica",
    "org": "m",
    "seiyuu": "mika"
  },
  {
    "name": "mika",
    "mmdd": "06-24",
    "kind": "seiyuu",
    "color": "#F4ADB7",
    "link": "",
    "org": "m",
    "seiyuu": ""
  },
  {
    "name": "八潮瑠唯",
    "mmdd": "11-19",
    "kind": "character",
    "color": "#669988",
    "link": "/orgs/morfonica",
    "org": "m",
    "seiyuu": "Ayasa"
  },
  {
    "name": "Ayasa",
    "mmdd": "10-19",
    "kind": "seiyuu",
    "color": "#A3C1B7",
    "link": "",
    "org": "m",
    "seiyuu": ""
  },
  {
    "name": "和奏瑞依",
    "mmdd": "01-13",
    "kind": "character",
    "color": "#CC0000",
    "link": "/orgs/raise-a-suilen",
    "org": "ras",
    "seiyuu": "Raychell"
  },
  {
    "name": "Raychell",
    "mmdd": "01-13",
    "kind": "seiyuu",
    "color": "#E06666",
    "link": "",
    "org": "ras",
    "seiyuu": ""
  },
  {
    "name": "朝日六花",
    "mmdd": "07-17",
    "kind": "character",
    "color": "#AAEE22",
    "link": "/orgs/raise-a-suilen",
    "org": "ras",
    "seiyuu": "小原莉子"
  },
  {
    "name": "小原莉子",
    "mmdd": "02-03",
    "kind": "seiyuu",
    "color": "#CCF47A",
    "link": "",
    "org": "ras",
    "seiyuu": ""
  },
  {
    "name": "佐藤益木",
    "mmdd": "05-12",
    "kind": "character",
    "color": "#EEBB44",
    "link": "/orgs/raise-a-suilen",
    "org": "ras",
    "seiyuu": "夏芽"
  },
  {
    "name": "夏芽",
    "mmdd": "07-20",
    "kind": "seiyuu",
    "color": "#F4D68E",
    "link": "",
    "org": "ras",
    "seiyuu": ""
  },
  {
    "name": "鳰原令王那",
    "mmdd": "03-25",
    "kind": "character",
    "color": "#FF99BB",
    "link": "/orgs/raise-a-suilen",
    "org": "ras",
    "seiyuu": "仓知玲凤"
  },
  {
    "name": "仓知玲凤",
    "mmdd": "05-22",
    "kind": "seiyuu",
    "color": "#FFC1D6",
    "link": "",
    "org": "ras",
    "seiyuu": ""
  },
  {
    "name": "珠手知由",
    "mmdd": "12-07",
    "kind": "character",
    "color": "#FF99BB",
    "link": "/orgs/raise-a-suilen",
    "org": "ras",
    "seiyuu": "纺木吏佐"
  },
  {
    "name": "纺木吏佐",
    "mmdd": "07-05",
    "kind": "seiyuu",
    "color": "#FFC1D6",
    "link": "",
    "org": "ras",
    "seiyuu": ""
  },
  {
    "name": "高松灯",
    "mmdd": "11-22",
    "kind": "character",
    "color": "#77BBDD",
    "link": "/orgs/mygo",
    "org": "mygo",
    "seiyuu": "羊宫妃那"
  },
  {
    "name": "羊宫妃那",
    "mmdd": "03-26",
    "kind": "seiyuu",
    "color": "#ADD6EA",
    "link": "",
    "org": "mygo",
    "seiyuu": ""
  },
  {
    "name": "千早爱音",
    "mmdd": "09-08",
    "kind": "character",
    "color": "#FF8899",
    "link": "/orgs/mygo",
    "org": "mygo",
    "seiyuu": "立石凛"
  },
  {
    "name": "立石凛",
    "mmdd": "07-10",
    "kind": "seiyuu",
    "color": "#FFB7C1",
    "link": "",
    "org": "mygo",
    "seiyuu": ""
  },
  {
    "name": "要乐奈",
    "mmdd": "02-22",
    "kind": "character",
    "color": "#77DD77",
    "link": "/orgs/mygo",
    "org": "mygo",
    "seiyuu": "青木阳菜"
  },
  {
    "name": "青木阳菜",
    "mmdd": "01-05",
    "kind": "seiyuu",
    "color": "#ADEAAD",
    "link": "",
    "org": "mygo",
    "seiyuu": ""
  },
  {
    "name": "长崎爽世",
    "mmdd": "05-27",
    "kind": "character",
    "color": "#FFDD88",
    "link": "/orgs/mygo",
    "org": "mygo",
    "seiyuu": "小日向美香"
  },
  {
    "name": "小日向美香",
    "mmdd": "03-14",
    "kind": "seiyuu",
    "color": "#FFEAB7",
    "link": "",
    "org": "mygo",
    "seiyuu": ""
  },
  {
    "name": "椎名立希",
    "mmdd": "08-09",
    "kind": "character",
    "color": "#7777AA",
    "link": "/orgs/mygo",
    "org": "mygo",
    "seiyuu": "林鼓子"
  },
  {
    "name": "林鼓子",
    "mmdd": "05-15",
    "kind": "seiyuu",
    "color": "#ADADCC",
    "link": "",
    "org": "mygo",
    "seiyuu": ""
  },
  {
    "name": "三角初华",
    "mmdd": "06-26",
    "kind": "character",
    "color": "#BB9955",
    "link": "/orgs/avemujica",
    "org": "ave",
    "seiyuu": "佐佐木李子"
  },
  {
    "name": "佐佐木李子",
    "mmdd": "11-10",
    "kind": "seiyuu",
    "color": "#D6C199",
    "link": "",
    "org": "ave",
    "seiyuu": ""
  },
  {
    "name": "若叶睦",
    "mmdd": "01-14",
    "kind": "character",
    "color": "#779977",
    "link": "/orgs/avemujica",
    "org": "ave",
    "seiyuu": "渡濑结月"
  },
  {
    "name": "渡濑结月",
    "mmdd": "02-18",
    "kind": "seiyuu",
    "color": "#ADC1AD",
    "link": "",
    "org": "ave",
    "seiyuu": ""
  },
  {
    "name": "八幡海铃",
    "mmdd": "04-07",
    "kind": "character",
    "color": "#335566",
    "link": "/orgs/avemujica",
    "org": "ave",
    "seiyuu": "冈田梦以"
  },
  {
    "name": "冈田梦以",
    "mmdd": "05-19",
    "kind": "seiyuu",
    "color": "#8499A3",
    "link": "",
    "org": "ave",
    "seiyuu": ""
  },
  {
    "name": "祐天寺若麦",
    "mmdd": "06-01",
    "kind": "character",
    "color": "#AA4477",
    "link": "/orgs/avemujica",
    "org": "ave",
    "seiyuu": "米泽茜"
  },
  {
    "name": "米泽茜",
    "mmdd": "12-31",
    "kind": "seiyuu",
    "color": "#CC8EAD",
    "link": "",
    "org": "ave",
    "seiyuu": ""
  },
  {
    "name": "丰川祥子",
    "mmdd": "02-14",
    "kind": "character",
    "color": "#7799CC",
    "link": "/orgs/avemujica",
    "org": "ave",
    "seiyuu": "高尾奏音"
  },
  {
    "name": "高尾奏音",
    "mmdd": "09-10",
    "kind": "seiyuu",
    "color": "#ADC1E0",
    "link": "",
    "org": "ave",
    "seiyuu": ""
  },
  {
    "name": "仲町阿拉蕾",
    "mmdd": "08-16",
    "kind": "character",
    "color": "#FFEE55",
    "link": "/orgs/yumemita",
    "org": "mxd",
    "seiyuu": ""
  },
  {
    "name": "宫永野乃花",
    "mmdd": "04-17",
    "kind": "character",
    "color": "#FFBBCC",
    "link": "/orgs/yumemita",
    "org": "mxd",
    "seiyuu": ""
  },
  {
    "name": "峰月律",
    "mmdd": "02-07",
    "kind": "character",
    "color": "#4477CC",
    "link": "/orgs/yumemita",
    "org": "mxd",
    "seiyuu": ""
  },
  {
    "name": "藤都子",
    "mmdd": "09-19",
    "kind": "character",
    "color": "#9977CC",
    "link": "/orgs/yumemita",
    "org": "mxd",
    "seiyuu": ""
  },
  {
    "name": "千石由乃",
    "mmdd": "11-04",
    "kind": "character",
    "color": "#EE5577",
    "link": "/orgs/yumemita",
    "org": "mxd",
    "seiyuu": ""
  },
  {
    "name": "汐见萤",
    "mmdd": "03-12",
    "kind": "character",
    "color": "#99FF99",
    "link": "/orgs/millsage",
    "org": "millsage",
    "seiyuu": "药师寺李有"
  },
  {
    "name": "药师寺李有",
    "mmdd": "09-11",
    "kind": "seiyuu",
    "color": "#C1FFC1",
    "link": "",
    "org": "millsage",
    "seiyuu": ""
  },
  {
    "name": "伊泽枣",
    "mmdd": "03-30",
    "kind": "character",
    "color": "#FF4444",
    "link": "/orgs/millsage",
    "org": "millsage",
    "seiyuu": "千春"
  },
  {
    "name": "千春",
    "mmdd": "04-10",
    "kind": "seiyuu",
    "color": "#FF8E8E",
    "link": "",
    "org": "millsage",
    "seiyuu": ""
  },
  {
    "name": "琴平凪",
    "mmdd": "12-10",
    "kind": "character",
    "color": "#5555FF",
    "link": "/orgs/millsage",
    "org": "millsage",
    "seiyuu": "结川麻希"
  },
  {
    "name": "结川麻希",
    "mmdd": "02-15",
    "kind": "seiyuu",
    "color": "#9999FF",
    "link": "",
    "org": "millsage",
    "seiyuu": ""
  },
  {
    "name": "滨崎茉幌",
    "mmdd": "07-16",
    "kind": "character",
    "color": "#77FFFF",
    "link": "/orgs/millsage",
    "org": "millsage",
    "seiyuu": "伊驹祐里惠"
  },
  {
    "name": "伊驹祐里惠",
    "mmdd": "02-24",
    "kind": "seiyuu",
    "color": "#ADFFFF",
    "link": "",
    "org": "millsage",
    "seiyuu": ""
  },
  {
    "name": "和泉朋花",
    "mmdd": "10-24",
    "kind": "character",
    "color": "#EE99EE",
    "link": "/orgs/millsage",
    "org": "millsage",
    "seiyuu": "咲川雏乃"
  },
  {
    "name": "咲川雏乃",
    "mmdd": "01-22",
    "kind": "seiyuu",
    "color": "#F4C1F4",
    "link": "",
    "org": "millsage",
    "seiyuu": ""
  },
  {
    "name": "须贺蕾叶",
    "mmdd": "07-28",
    "kind": "character",
    "color": "#FF7700",
    "link": "/orgs/ikka-dumb-rock",
    "org": "dumb",
    "seiyuu": "橘芽衣"
  },
  {
    "name": "橘芽衣",
    "mmdd": "11-19",
    "kind": "seiyuu",
    "color": "#FFAD66",
    "link": "",
    "org": "dumb",
    "seiyuu": ""
  },
  {
    "name": "马桥心玖",
    "mmdd": "10-04",
    "kind": "character",
    "color": "#22CCFF",
    "link": "/orgs/ikka-dumb-rock",
    "org": "dumb",
    "seiyuu": "凉泉樱花"
  },
  {
    "name": "凉泉樱花",
    "mmdd": "03-05",
    "kind": "seiyuu",
    "color": "#7AE0FF",
    "link": "",
    "org": "dumb",
    "seiyuu": ""
  },
  {
    "name": "矢仓蓬咲",
    "mmdd": "05-06",
    "kind": "character",
    "color": "#448888",
    "link": "/orgs/ikka-dumb-rock",
    "org": "dumb",
    "seiyuu": "花宫初奈"
  },
  {
    "name": "花宫初奈",
    "mmdd": "10-24",
    "kind": "seiyuu",
    "color": "#8EB7B7",
    "link": "",
    "org": "dumb",
    "seiyuu": ""
  },
  {
    "name": "梅里千樱梨",
    "mmdd": "04-02",
    "kind": "character",
    "color": "#FF55AA",
    "link": "/orgs/ikka-dumb-rock",
    "org": "dumb",
    "seiyuu": "菱川花菜"
  },
  {
    "name": "菱川花菜",
    "mmdd": "05-19",
    "kind": "seiyuu",
    "color": "#FF99CC",
    "link": "",
    "org": "dumb",
    "seiyuu": ""
  },
  {
    "name": "四宫宁月",
    "mmdd": "03-05",
    "kind": "character",
    "color": "#9999FF",
    "link": "/orgs/ikka-dumb-rock",
    "org": "dumb",
    "seiyuu": "远野光"
  },
  {
    "name": "远野光",
    "mmdd": "03-05",
    "kind": "seiyuu",
    "color": "#C1C1FF",
    "link": "",
    "org": "dumb",
    "seiyuu": ""
  }
]
